odoo/addons/l10n_it_pos_fatturapa_send_directly/README.rst
odoo/addons/l10n_it_pos_fatturapa_send_directly/__init__.py
odoo/addons/l10n_it_pos_fatturapa_send_directly/__manifest__.py
odoo/addons/l10n_it_pos_fatturapa_send_directly/i18n/l10n_it_pos_fatturapa_send_directly.pot
odoo/addons/l10n_it_pos_fatturapa_send_directly/models/__init__.py
odoo/addons/l10n_it_pos_fatturapa_send_directly/models/pos_order.py
odoo/addons/l10n_it_pos_fatturapa_send_directly/readme/CONTRIBUTORS.rst
odoo/addons/l10n_it_pos_fatturapa_send_directly/readme/DESCRIPTION.rst
odoo/addons/l10n_it_pos_fatturapa_send_directly/static/description/icon.png
odoo/addons/l10n_it_pos_fatturapa_send_directly/static/description/index.html
odoo12_addon_l10n_it_pos_fatturapa_send_directly-12.0.2.0.0.dist-info/METADATA
odoo12_addon_l10n_it_pos_fatturapa_send_directly-12.0.2.0.0.dist-info/WHEEL
odoo12_addon_l10n_it_pos_fatturapa_send_directly-12.0.2.0.0.dist-info/top_level.txt
odoo12_addon_l10n_it_pos_fatturapa_send_directly-12.0.2.0.0.dist-info/RECORD
